{
	"door": {
		"name": "Door",
		"sprite_path": "res://Chapters1&2/Assets/door.jpeg",
		"lines": [
			"Doki: The door is locked.",
			"Doki: Thus, no leave",
			"Door: ..."
		]
	},
	"pictures": {
		"name": "Pictures",
		"sprite_path": "res://Chapters1&2/Assets/pictures.jpeg",
		"lines": [
			"Doki: Dog",
			"Doki: Objection, it's dawg",
			"Pictures: ...??"
		]
	},
	"bookcase": {
		"name": "Bookcase",
		"sprite_path": "res://Chapters1&2/Assets/bookcase.jpg",
		"lines": [
			"Doki: Books be here. Okay"
		]
	},
	"dragoon": {
		"name": "Dragoon",
		"sprite_path": "res://Chapters1&2/Assets/Dragoon.png",
		"lines": [
			"Dragoon: I am a Dragoon. mhm. frfr",
			"Dragoon: Doki is my goddess. mhm. frfr",
			"Doki: ...real shit"
		],
	},
	"character": {
		"name": "",
		"sprite_path": "",
		"lines": [
			"",
			"Doki: "
		]
	},
}
